urdfModifiers/__init__.py
urdfModifiers/core/__init__.py
urdfModifiers/core/fixedOffsetModifier.py
urdfModifiers/core/jointModifier.py
urdfModifiers/core/linkModifier.py
urdfModifiers/core/modification.py
urdfModifiers/core/modifier.py
urdfModifiers/geometry/__init__.py
urdfModifiers/geometry/geometry.py
urdfModifiers/utils/__init__.py
urdfModifiers/utils/utils.py
urdf_modifiers-0.0.2.dist-info/METADATA
urdf_modifiers-0.0.2.dist-info/WHEEL
urdf_modifiers-0.0.2.dist-info/top_level.txt
urdf_modifiers-0.0.2.dist-info/RECORD
